parallelm/__init__.py
parallelm/mlops/__init__.py
parallelm/mlops/base_obj.py
parallelm/mlops/config_info.py
parallelm/mlops/constants.py
parallelm/mlops/data_frame.py
parallelm/mlops/data_to_json.py
parallelm/mlops/logger_factory.py
parallelm/mlops/metrics_constants.py
parallelm/mlops/mlhealth.py
parallelm/mlops/mlops.py
parallelm/mlops/mlops_ctx.py
parallelm/mlops/mlops_env_constants.py
parallelm/mlops/mlops_exception.py
parallelm/mlops/mlops_metrics.py
parallelm/mlops/mlops_mode.py
parallelm/mlops/mlops_rest_connected.py
parallelm/mlops/mlops_rest_factory.py
parallelm/mlops/mlops_rest_interfaces.py
parallelm/mlops/mlops_rest_standalone.py
parallelm/mlops/packer.py
parallelm/mlops/predefined_stats.py
parallelm/mlops/singelton.py
parallelm/mlops/stats_category.py
parallelm/mlops/utils.py
parallelm/mlops/versions.py
parallelm/mlops/versions_info.py
parallelm/mlops/channels/__init__.py
parallelm/mlops/channels/file_channel.py
parallelm/mlops/channels/mlops_channel.py
parallelm/mlops/channels/mlops_pyspark_channel.py
parallelm/mlops/channels/mlops_python_channel.py
parallelm/mlops/channels/python_accumulator_channel.py
parallelm/mlops/channels/python_channel_health.py
parallelm/mlops/common/__init__.py
parallelm/mlops/common/spark_pipeline_model_helper.py
parallelm/mlops/common/string_ops.py
parallelm/mlops/data_analysis/__init__.py
parallelm/mlops/data_analysis/categorical_data_analyst.py
parallelm/mlops/data_analysis/continuous_data_analyst.py
parallelm/mlops/e2e_tests/__init__.py
parallelm/mlops/e2e_tests/e2e_constants.py
parallelm/mlops/e2e_tests/predict_node.py
parallelm/mlops/e2e_tests/train_node.py
parallelm/mlops/e2e_tests/health_node/__init__.py
parallelm/mlops/e2e_tests/health_node/runner.py
parallelm/mlops/e2e_tests/health_node/test_events.py
parallelm/mlops/e2e_tests/health_node/test_ion_structure.py
parallelm/mlops/e2e_tests/health_node/test_models.py
parallelm/mlops/e2e_tests/health_node/test_stats.py
parallelm/mlops/events/__init__.py
ml_ops-1.2.1.dist-info/METADATA
ml_ops-1.2.1.dist-info/WHEEL
ml_ops-1.2.1.dist-info/top_level.txt
ml_ops-1.2.1.dist-info/RECORD
