Metadata-Version: 2.1
Name: ml-ops
Version: 1.2.1
Summary: A library to read and report MLApp statistics
Home-page: https://mlpiper.github.io/mlpiper/mlops/
Author: ParallelM
Author-email: info@parallelm.com
License: Apache License 2.0
Platform: UNKNOWN
Classifier: Programming Language :: Python :: 2
Classifier: Programming Language :: Python :: 3
Classifier: License :: OSI Approved :: Apache Software License
Classifier: Operating System :: MacOS
Classifier: Operating System :: POSIX
Classifier: Operating System :: Unix
Requires-Python: >=2.7, !=3.0.*, !=3.1.*, !=3.2.*, !=3.3.*
Requires-Dist: wheel
Requires-Dist: pandas
Requires-Dist: termcolor
Requires-Dist: kazoo
Requires-Dist: protobuf
Requires-Dist: requests
Requires-Dist: py4j
Requires-Dist: scikit-learn
Requires-Dist: numpy
Requires-Dist: future
